{"pageProps":{"_nextI18Next":{"initialI18nStore":{"en":{"common":{},"chocobo-color":{"_title":"Chocobo Color","_description":"Calculator for changing your chocobo’s color.","calculator":"Calculator","currentStain":"Current color","targetStain":"Desired color","calculate":"Calculate","fruitsNeeded":"Fruits needed","fruitsOrder":"Feeding order","noFruits":"No fruits needed","aboutPage":{"_title":"About"}}}},"initialLocale":"en","userConfig":{"i18n":{"defaultLocale":"en","locales":["en","de","fr","ja","cn","ko"]},"react":{"useSuspense":false},"default":{"i18n":{"defaultLocale":"en","locales":["en","de","fr","ja","cn","ko"]},"react":{"useSuspense":false}}}}},"__N_SSG":true}