{"data":{"biteTimes":[{"itemId":29775,"spot":242,"baitId":2591,"biteTime":2,"occurences":51},{"itemId":29775,"spot":242,"baitId":2591,"biteTime":2,"occurences":54},{"itemId":29775,"spot":242,"baitId":2591,"biteTime":2,"occurences":61},{"itemId":29775,"spot":242,"baitId":2591,"biteTime":2,"occurences":72},{"itemId":29768,"spot":242,"baitId":2591,"biteTime":2,"occurences":1},{"itemId":29775,"spot":242,"baitId":2591,"biteTime":2,"occurences":43},{"itemId":29772,"spot":242,"baitId":2591,"biteTime":2,"occurences":1},{"itemId":29775,"spot":242,"baitId":2591,"biteTime":2,"occurences":37},{"itemId":29775,"spot":242,"baitId":2591,"biteTime":2,"occurences":28},{"itemId":29772,"spot":242,"baitId":2591,"biteTime":2,"occurences":4},{"itemId":29775,"spot":242,"baitId":2591,"biteTime":2,"occurences":10},{"itemId":29772,"spot":242,"baitId":2591,"biteTime":2,"occurences":6},{"itemId":29775,"spot":242,"baitId":2591,"biteTime":2,"occurences":6},{"itemId":29772,"spot":242,"baitId":2591,"biteTime":2,"occurences":4},{"itemId":29775,"spot":242,"baitId":2591,"biteTime":2,"occurences":2},{"itemId":29772,"spot":242,"baitId":2591,"biteTime":3,"occurences":8},{"itemId":29775,"spot":242,"baitId":2591,"biteTime":3,"occurences":2},{"itemId":29772,"spot":242,"baitId":2591,"biteTime":3,"occurences":4},{"itemId":29772,"spot":242,"baitId":2591,"biteTime":3,"occurences":8},{"itemId":29769,"spot":242,"baitId":2591,"biteTime":3,"occurences":1},{"itemId":29772,"spot":242,"baitId":2591,"biteTime":3,"occurences":14},{"itemId":29772,"spot":242,"baitId":2591,"biteTime":3,"occurences":23},{"itemId":29775,"spot":242,"baitId":2591,"biteTime":3,"occurences":1},{"itemId":29772,"spot":242,"baitId":2591,"biteTime":3,"occurences":17},{"itemId":29772,"spot":242,"baitId":2591,"biteTime":3,"occurences":16},{"itemId":29772,"spot":242,"baitId":2591,"biteTime":3,"occurences":37},{"itemId":29772,"spot":242,"baitId":2591,"biteTime":3,"occurences":22},{"itemId":29772,"spot":242,"baitId":2591,"biteTime":3,"occurences":25},{"itemId":29768,"spot":242,"baitId":2591,"biteTime":4,"occurences":1},{"itemId":29769,"spot":242,"baitId":2591,"biteTime":4,"occurences":1},{"itemId":29772,"spot":242,"baitId":2591,"biteTime":4,"occurences":31},{"itemId":29769,"spot":242,"baitId":2591,"biteTime":4,"occurences":1},{"itemId":29772,"spot":242,"baitId":2591,"biteTime":4,"occurences":23},{"itemId":29769,"spot":242,"baitId":2591,"biteTime":4,"occurences":2},{"itemId":29772,"spot":242,"baitId":2591,"biteTime":4,"occurences":23},{"itemId":29767,"spot":242,"baitId":2591,"biteTime":4,"occurences":1},{"itemId":29769,"spot":242,"baitId":2591,"biteTime":4,"occurences":2},{"itemId":29772,"spot":242,"baitId":2591,"biteTime":4,"occurences":31},{"itemId":29769,"spot":242,"baitId":2591,"biteTime":4,"occurences":2},{"itemId":29772,"spot":242,"baitId":2591,"biteTime":4,"occurences":26},{"itemId":29768,"spot":242,"baitId":2591,"biteTime":4,"occurences":1},{"itemId":29769,"spot":242,"baitId":2591,"biteTime":4,"occurences":3},{"itemId":29772,"spot":242,"baitId":2591,"biteTime":4,"occurences":31},{"itemId":29769,"spot":242,"baitId":2591,"biteTime":4,"occurences":4},{"itemId":29772,"spot":242,"baitId":2591,"biteTime":4,"occurences":33},{"itemId":29768,"spot":242,"baitId":2591,"biteTime":4,"occurences":2},{"itemId":29769,"spot":242,"baitId":2591,"biteTime":4,"occurences":5},{"itemId":29772,"spot":242,"baitId":2591,"biteTime":4,"occurences":19},{"itemId":29768,"spot":242,"baitId":2591,"biteTime":4,"occurences":2},{"itemId":29769,"spot":242,"baitId":2591,"biteTime":4,"occurences":6},{"itemId":29772,"spot":242,"baitId":2591,"biteTime":4,"occurences":26},{"itemId":29768,"spot":242,"baitId":2591,"biteTime":4,"occurences":1},{"itemId":29769,"spot":242,"baitId":2591,"biteTime":4,"occurences":17},{"itemId":29772,"spot":242,"baitId":2591,"biteTime":4,"occurences":20},{"itemId":29768,"spot":242,"baitId":2591,"biteTime":5,"occurences":1},{"itemId":29769,"spot":242,"baitId":2591,"biteTime":5,"occurences":11},{"itemId":29772,"spot":242,"baitId":2591,"biteTime":5,"occurences":31},{"itemId":29768,"spot":242,"baitId":2591,"biteTime":5,"occurences":3},{"itemId":29769,"spot":242,"baitId":2591,"biteTime":5,"occurences":16},{"itemId":29772,"spot":242,"baitId":2591,"biteTime":5,"occurences":21},{"itemId":29768,"spot":242,"baitId":2591,"biteTime":5,"occurences":2},{"itemId":29769,"spot":242,"baitId":2591,"biteTime":5,"occurences":20},{"itemId":29772,"spot":242,"baitId":2591,"biteTime":5,"occurences":16},{"itemId":29768,"spot":242,"baitId":2591,"biteTime":5,"occurences":4},{"itemId":29769,"spot":242,"baitId":2591,"biteTime":5,"occurences":19},{"itemId":29772,"spot":242,"baitId":2591,"biteTime":5,"occurences":20},{"itemId":29768,"spot":242,"baitId":2591,"biteTime":5,"occurences":10},{"itemId":29769,"spot":242,"baitId":2591,"biteTime":5,"occurences":19},{"itemId":29772,"spot":242,"baitId":2591,"biteTime":5,"occurences":24},{"itemId":29780,"spot":242,"baitId":2591,"biteTime":5,"occurences":1},{"itemId":29768,"spot":242,"baitId":2591,"biteTime":5,"occurences":4},{"itemId":29769,"spot":242,"baitId":2591,"biteTime":5,"occurences":15},{"itemId":29772,"spot":242,"baitId":2591,"biteTime":5,"occurences":18},{"itemId":29780,"spot":242,"baitId":2591,"biteTime":5,"occurences":1},{"itemId":29768,"spot":242,"baitId":2591,"biteTime":5,"occurences":13},{"itemId":29769,"spot":242,"baitId":2591,"biteTime":5,"occurences":20},{"itemId":29772,"spot":242,"baitId":2591,"biteTime":5,"occurences":4},{"itemId":29780,"spot":242,"baitId":2591,"biteTime":5,"occurences":1},{"itemId":29768,"spot":242,"baitId":2591,"biteTime":5,"occurences":28},{"itemId":29769,"spot":242,"baitId":2591,"biteTime":5,"occurences":17},{"itemId":29772,"spot":242,"baitId":2591,"biteTime":5,"occurences":3},{"itemId":29780,"spot":242,"baitId":2591,"biteTime":5,"occurences":2},{"itemId":29768,"spot":242,"baitId":2591,"biteTime":5,"occurences":20},{"itemId":29769,"spot":242,"baitId":2591,"biteTime":5,"occurences":14},{"itemId":29772,"spot":242,"baitId":2591,"biteTime":5,"occurences":2},{"itemId":29780,"spot":242,"baitId":2591,"biteTime":5,"occurences":1},{"itemId":29768,"spot":242,"baitId":2591,"biteTime":5,"occurences":23},{"itemId":29769,"spot":242,"baitId":2591,"biteTime":5,"occurences":19},{"itemId":29780,"spot":242,"baitId":2591,"biteTime":5,"occurences":3},{"itemId":29768,"spot":242,"baitId":2591,"biteTime":6,"occurences":19},{"itemId":29769,"spot":242,"baitId":2591,"biteTime":6,"occurences":10},{"itemId":29772,"spot":242,"baitId":2591,"biteTime":6,"occurences":1},{"itemId":29780,"spot":242,"baitId":2591,"biteTime":6,"occurences":1},{"itemId":29768,"spot":242,"baitId":2591,"biteTime":6,"occurences":25},{"itemId":29769,"spot":242,"baitId":2591,"biteTime":6,"occurences":21},{"itemId":29780,"spot":242,"baitId":2591,"biteTime":6,"occurences":5},{"itemId":29768,"spot":242,"baitId":2591,"biteTime":6,"occurences":17},{"itemId":29769,"spot":242,"baitId":2591,"biteTime":6,"occurences":15},{"itemId":29780,"spot":242,"baitId":2591,"biteTime":6,"occurences":5},{"itemId":29768,"spot":242,"baitId":2591,"biteTime":6,"occurences":11},{"itemId":29769,"spot":242,"baitId":2591,"biteTime":6,"occurences":22},{"itemId":29780,"spot":242,"baitId":2591,"biteTime":6,"occurences":6},{"itemId":29768,"spot":242,"baitId":2591,"biteTime":6,"occurences":19},{"itemId":29769,"spot":242,"baitId":2591,"biteTime":6,"occurences":7},{"itemId":29780,"spot":242,"baitId":2591,"biteTime":6,"occurences":10},{"itemId":29768,"spot":242,"baitId":2591,"biteTime":6,"occurences":18},{"itemId":29769,"spot":242,"baitId":2591,"biteTime":6,"occurences":15},{"itemId":29780,"spot":242,"baitId":2591,"biteTime":6,"occurences":20},{"itemId":29768,"spot":242,"baitId":2591,"biteTime":6,"occurences":11},{"itemId":29769,"spot":242,"baitId":2591,"biteTime":6,"occurences":14},{"itemId":29780,"spot":242,"baitId":2591,"biteTime":6,"occurences":13},{"itemId":29768,"spot":242,"baitId":2591,"biteTime":6,"occurences":20},{"itemId":29769,"spot":242,"baitId":2591,"biteTime":6,"occurences":25},{"itemId":29780,"spot":242,"baitId":2591,"biteTime":6,"occurences":13},{"itemId":29768,"spot":242,"baitId":2591,"biteTime":6,"occurences":15},{"itemId":29769,"spot":242,"baitId":2591,"biteTime":6,"occurences":22},{"itemId":29780,"spot":242,"baitId":2591,"biteTime":6,"occurences":11},{"itemId":29768,"spot":242,"baitId":2591,"biteTime":6,"occurences":17},{"itemId":29769,"spot":242,"baitId":2591,"biteTime":6,"occurences":10},{"itemId":29780,"spot":242,"baitId":2591,"biteTime":6,"occurences":11},{"itemId":29768,"spot":242,"baitId":2591,"biteTime":7,"occurences":11},{"itemId":29769,"spot":242,"baitId":2591,"biteTime":7,"occurences":20},{"itemId":29780,"spot":242,"baitId":2591,"biteTime":7,"occurences":10},{"itemId":29768,"spot":242,"baitId":2591,"biteTime":7,"occurences":8},{"itemId":29769,"spot":242,"baitId":2591,"biteTime":7,"occurences":18},{"itemId":29780,"spot":242,"baitId":2591,"biteTime":7,"occurences":14},{"itemId":29768,"spot":242,"baitId":2591,"biteTime":7,"occurences":6},{"itemId":29769,"spot":242,"baitId":2591,"biteTime":7,"occurences":19},{"itemId":29780,"spot":242,"baitId":2591,"biteTime":7,"occurences":7},{"itemId":29768,"spot":242,"baitId":2591,"biteTime":7,"occurences":1},{"itemId":29769,"spot":242,"baitId":2591,"biteTime":7,"occurences":21},{"itemId":29780,"spot":242,"baitId":2591,"biteTime":7,"occurences":10},{"itemId":29769,"spot":242,"baitId":2591,"biteTime":7,"occurences":16},{"itemId":29780,"spot":242,"baitId":2591,"biteTime":7,"occurences":7},{"itemId":29769,"spot":242,"baitId":2591,"biteTime":7,"occurences":14},{"itemId":29775,"spot":242,"baitId":2591,"biteTime":7,"occurences":1},{"itemId":29780,"spot":242,"baitId":2591,"biteTime":7,"occurences":12},{"itemId":29769,"spot":242,"baitId":2591,"biteTime":7,"occurences":12},{"itemId":29780,"spot":242,"baitId":2591,"biteTime":7,"occurences":11},{"itemId":29769,"spot":242,"baitId":2591,"biteTime":7,"occurences":17},{"itemId":29780,"spot":242,"baitId":2591,"biteTime":7,"occurences":16},{"itemId":29769,"spot":242,"baitId":2591,"biteTime":7,"occurences":11},{"itemId":29780,"spot":242,"baitId":2591,"biteTime":7,"occurences":10},{"itemId":29769,"spot":242,"baitId":2591,"biteTime":7,"occurences":13},{"itemId":29780,"spot":242,"baitId":2591,"biteTime":7,"occurences":10},{"itemId":29769,"spot":242,"baitId":2591,"biteTime":8,"occurences":16},{"itemId":29780,"spot":242,"baitId":2591,"biteTime":8,"occurences":10},{"itemId":29769,"spot":242,"baitId":2591,"biteTime":8,"occurences":16},{"itemId":29780,"spot":242,"baitId":2591,"biteTime":8,"occurences":9},{"itemId":29769,"spot":242,"baitId":2591,"biteTime":8,"occurences":15},{"itemId":29780,"spot":242,"baitId":2591,"biteTime":8,"occurences":13},{"itemId":29769,"spot":242,"baitId":2591,"biteTime":8,"occurences":10},{"itemId":29780,"spot":242,"baitId":2591,"biteTime":8,"occurences":5},{"itemId":29769,"spot":242,"baitId":2591,"biteTime":8,"occurences":7},{"itemId":29780,"spot":242,"baitId":2591,"biteTime":8,"occurences":16},{"itemId":29769,"spot":242,"baitId":2591,"biteTime":8,"occurences":18},{"itemId":29780,"spot":242,"baitId":2591,"biteTime":8,"occurences":11},{"itemId":29769,"spot":242,"baitId":2591,"biteTime":8,"occurences":6},{"itemId":29769,"spot":242,"baitId":2591,"biteTime":8,"occurences":1},{"itemId":29780,"spot":242,"baitId":2591,"biteTime":8,"occurences":1},{"itemId":29780,"spot":242,"baitId":2591,"biteTime":8,"occurences":1},{"itemId":29790,"spot":242,"baitId":2591,"biteTime":9,"occurences":1},{"itemId":29790,"spot":242,"baitId":2591,"biteTime":10,"occurences":1},{"itemId":29790,"spot":242,"baitId":2591,"biteTime":10,"occurences":1},{"itemId":29790,"spot":242,"baitId":2591,"biteTime":10,"occurences":1},{"itemId":29790,"spot":242,"baitId":2591,"biteTime":10,"occurences":1},{"itemId":29790,"spot":242,"baitId":2591,"biteTime":10,"occurences":1},{"itemId":29790,"spot":242,"baitId":2591,"biteTime":10,"occurences":1},{"itemId":29790,"spot":242,"baitId":2591,"biteTime":10,"occurences":2},{"itemId":29790,"spot":242,"baitId":2591,"biteTime":11,"occurences":1},{"itemId":29790,"spot":242,"baitId":2591,"biteTime":11,"occurences":1},{"itemId":29790,"spot":242,"baitId":2591,"biteTime":11,"occurences":1},{"itemId":29790,"spot":242,"baitId":2591,"biteTime":11,"occurences":1},{"itemId":29790,"spot":242,"baitId":2591,"biteTime":12,"occurences":1},{"itemId":29790,"spot":242,"baitId":2591,"biteTime":12,"occurences":1},{"itemId":29790,"spot":242,"baitId":2591,"biteTime":12,"occurences":2},{"itemId":29772,"spot":242,"baitId":2591,"biteTime":16,"occurences":1},{"itemId":29768,"spot":242,"baitId":29714,"biteTime":2,"occurences":6},{"itemId":29769,"spot":242,"baitId":29714,"biteTime":2,"occurences":1},{"itemId":29775,"spot":242,"baitId":29714,"biteTime":2,"occurences":46},{"itemId":29768,"spot":242,"baitId":29714,"biteTime":2,"occurences":17},{"itemId":29775,"spot":242,"baitId":29714,"biteTime":2,"occurences":53},{"itemId":29768,"spot":242,"baitId":29714,"biteTime":2,"occurences":14},{"itemId":29774,"spot":242,"baitId":29714,"biteTime":2,"occurences":1},{"itemId":29775,"spot":242,"baitId":29714,"biteTime":2,"occurences":49},{"itemId":29768,"spot":242,"baitId":29714,"biteTime":2,"occurences":16},{"itemId":29769,"spot":242,"baitId":29714,"biteTime":2,"occurences":1},{"itemId":29775,"spot":242,"baitId":29714,"biteTime":2,"occurences":51},{"itemId":29768,"spot":242,"baitId":29714,"biteTime":2,"occurences":17},{"itemId":29772,"spot":242,"baitId":29714,"biteTime":2,"occurences":2},{"itemId":29775,"spot":242,"baitId":29714,"biteTime":2,"occurences":43},{"itemId":29768,"spot":242,"baitId":29714,"biteTime":2,"occurences":22},{"itemId":29772,"spot":242,"baitId":29714,"biteTime":2,"occurences":3},{"itemId":29775,"spot":242,"baitId":29714,"biteTime":2,"occurences":65},{"itemId":29780,"spot":242,"baitId":29714,"biteTime":2,"occurences":1},{"itemId":29768,"spot":242,"baitId":29714,"biteTime":2,"occurences":32},{"itemId":29772,"spot":242,"baitId":29714,"biteTime":2,"occurences":2},{"itemId":29775,"spot":242,"baitId":29714,"biteTime":2,"occurences":25},{"itemId":29780,"spot":242,"baitId":29714,"biteTime":2,"occurences":1},{"itemId":29768,"spot":242,"baitId":29714,"biteTime":2,"occurences":50},{"itemId":29772,"spot":242,"baitId":29714,"biteTime":2,"occurences":4},{"itemId":29775,"spot":242,"baitId":29714,"biteTime":2,"occurences":6},{"itemId":29780,"spot":242,"baitId":29714,"biteTime":2,"occurences":3},{"itemId":29768,"spot":242,"baitId":29714,"biteTime":2,"occurences":70},{"itemId":29772,"spot":242,"baitId":29714,"biteTime":2,"occurences":6},{"itemId":29774,"spot":242,"baitId":29714,"biteTime":2,"occurences":1},{"itemId":29775,"spot":242,"baitId":29714,"biteTime":2,"occurences":5},{"itemId":29780,"spot":242,"baitId":29714,"biteTime":2,"occurences":1},{"itemId":29768,"spot":242,"baitId":29714,"biteTime":2,"occurences":69},{"itemId":29772,"spot":242,"baitId":29714,"biteTime":2,"occurences":3},{"itemId":29780,"spot":242,"baitId":29714,"biteTime":2,"occurences":10},{"itemId":29768,"spot":242,"baitId":29714,"biteTime":3,"occurences":62},{"itemId":29772,"spot":242,"baitId":29714,"biteTime":3,"occurences":8},{"itemId":29775,"spot":242,"baitId":29714,"biteTime":3,"occurences":1},{"itemId":29780,"spot":242,"baitId":29714,"biteTime":3,"occurences":11},{"itemId":29768,"spot":242,"baitId":29714,"biteTime":3,"occurences":50},{"itemId":29772,"spot":242,"baitId":29714,"biteTime":3,"occurences":9},{"itemId":29780,"spot":242,"baitId":29714,"biteTime":3,"occurences":10},{"itemId":29768,"spot":242,"baitId":29714,"biteTime":3,"occurences":67},{"itemId":29772,"spot":242,"baitId":29714,"biteTime":3,"occurences":8},{"itemId":29780,"spot":242,"baitId":29714,"biteTime":3,"occurences":7},{"itemId":29768,"spot":242,"baitId":29714,"biteTime":3,"occurences":50},{"itemId":29772,"spot":242,"baitId":29714,"biteTime":3,"occurences":10},{"itemId":29780,"spot":242,"baitId":29714,"biteTime":3,"occurences":15},{"itemId":29768,"spot":242,"baitId":29714,"biteTime":3,"occurences":52},{"itemId":29772,"spot":242,"baitId":29714,"biteTime":3,"occurences":17},{"itemId":29780,"spot":242,"baitId":29714,"biteTime":3,"occurences":18},{"itemId":29768,"spot":242,"baitId":29714,"biteTime":3,"occurences":47},{"itemId":29772,"spot":242,"baitId":29714,"biteTime":3,"occurences":14},{"itemId":29780,"spot":242,"baitId":29714,"biteTime":3,"occurences":35},{"itemId":29768,"spot":242,"baitId":29714,"biteTime":3,"occurences":43},{"itemId":29772,"spot":242,"baitId":29714,"biteTime":3,"occurences":23},{"itemId":29780,"spot":242,"baitId":29714,"biteTime":3,"occurences":27},{"itemId":29768,"spot":242,"baitId":29714,"biteTime":3,"occurences":51},{"itemId":29772,"spot":242,"baitId":29714,"biteTime":3,"occurences":18},{"itemId":29780,"spot":242,"baitId":29714,"biteTime":3,"occurences":22},{"itemId":29768,"spot":242,"baitId":29714,"biteTime":3,"occurences":44},{"itemId":29772,"spot":242,"baitId":29714,"biteTime":3,"occurences":26},{"itemId":29780,"spot":242,"baitId":29714,"biteTime":3,"occurences":23},{"itemId":29768,"spot":242,"baitId":29714,"biteTime":3,"occurences":32},{"itemId":29772,"spot":242,"baitId":29714,"biteTime":3,"occurences":30},{"itemId":29780,"spot":242,"baitId":29714,"biteTime":3,"occurences":30},{"itemId":29768,"spot":242,"baitId":29714,"biteTime":4,"occurences":28},{"itemId":29772,"spot":242,"baitId":29714,"biteTime":4,"occurences":27},{"itemId":29780,"spot":242,"baitId":29714,"biteTime":4,"occurences":14},{"itemId":29768,"spot":242,"baitId":29714,"biteTime":4,"occurences":20},{"itemId":29769,"spot":242,"baitId":29714,"biteTime":4,"occurences":2},{"itemId":29772,"spot":242,"baitId":29714,"biteTime":4,"occurences":26},{"itemId":29780,"spot":242,"baitId":29714,"biteTime":4,"occurences":21},{"itemId":29767,"spot":242,"baitId":29714,"biteTime":4,"occurences":1},{"itemId":29768,"spot":242,"baitId":29714,"biteTime":4,"occurences":8},{"itemId":29772,"spot":242,"baitId":29714,"biteTime":4,"occurences":36},{"itemId":29780,"spot":242,"baitId":29714,"biteTime":4,"occurences":21},{"itemId":29768,"spot":242,"baitId":29714,"biteTime":4,"occurences":1},{"itemId":29769,"spot":242,"baitId":29714,"biteTime":4,"occurences":2},{"itemId":29772,"spot":242,"baitId":29714,"biteTime":4,"occurences":28},{"itemId":29774,"spot":242,"baitId":29714,"biteTime":4,"occurences":2},{"itemId":29780,"spot":242,"baitId":29714,"biteTime":4,"occurences":32},{"itemId":29768,"spot":242,"baitId":29714,"biteTime":4,"occurences":1},{"itemId":29769,"spot":242,"baitId":29714,"biteTime":4,"occurences":6},{"itemId":29772,"spot":242,"baitId":29714,"biteTime":4,"occurences":20},{"itemId":29774,"spot":242,"baitId":29714,"biteTime":4,"occurences":2},{"itemId":29780,"spot":242,"baitId":29714,"biteTime":4,"occurences":34},{"itemId":29769,"spot":242,"baitId":29714,"biteTime":4,"occurences":4},{"itemId":29772,"spot":242,"baitId":29714,"biteTime":4,"occurences":31},{"itemId":29774,"spot":242,"baitId":29714,"biteTime":4,"occurences":5},{"itemId":29780,"spot":242,"baitId":29714,"biteTime":4,"occurences":28},{"itemId":29769,"spot":242,"baitId":29714,"biteTime":4,"occurences":5},{"itemId":29772,"spot":242,"baitId":29714,"biteTime":4,"occurences":23},{"itemId":29774,"spot":242,"baitId":29714,"biteTime":4,"occurences":4},{"itemId":29780,"spot":242,"baitId":29714,"biteTime":4,"occurences":33},{"itemId":29769,"spot":242,"baitId":29714,"biteTime":4,"occurences":9},{"itemId":29772,"spot":242,"baitId":29714,"biteTime":4,"occurences":29},{"itemId":29774,"spot":242,"baitId":29714,"biteTime":4,"occurences":10},{"itemId":29780,"spot":242,"baitId":29714,"biteTime":4,"occurences":19},{"itemId":29769,"spot":242,"baitId":29714,"biteTime":4,"occurences":6},{"itemId":29772,"spot":242,"baitId":29714,"biteTime":4,"occurences":26},{"itemId":29774,"spot":242,"baitId":29714,"biteTime":4,"occurences":3},{"itemId":29780,"spot":242,"baitId":29714,"biteTime":4,"occurences":32},{"itemId":29769,"spot":242,"baitId":29714,"biteTime":4,"occurences":18},{"itemId":29772,"spot":242,"baitId":29714,"biteTime":4,"occurences":21},{"itemId":29774,"spot":242,"baitId":29714,"biteTime":4,"occurences":11},{"itemId":29780,"spot":242,"baitId":29714,"biteTime":4,"occurences":32},{"itemId":29769,"spot":242,"baitId":29714,"biteTime":5,"occurences":16},{"itemId":29772,"spot":242,"baitId":29714,"biteTime":5,"occurences":24},{"itemId":29774,"spot":242,"baitId":29714,"biteTime":5,"occurences":7},{"itemId":29780,"spot":242,"baitId":29714,"biteTime":5,"occurences":25},{"itemId":29769,"spot":242,"baitId":29714,"biteTime":5,"occurences":9},{"itemId":29772,"spot":242,"baitId":29714,"biteTime":5,"occurences":19},{"itemId":29774,"spot":242,"baitId":29714,"biteTime":5,"occurences":11},{"itemId":29780,"spot":242,"baitId":29714,"biteTime":5,"occurences":25},{"itemId":29769,"spot":242,"baitId":29714,"biteTime":5,"occurences":14},{"itemId":29772,"spot":242,"baitId":29714,"biteTime":5,"occurences":24},{"itemId":29774,"spot":242,"baitId":29714,"biteTime":5,"occurences":8},{"itemId":29780,"spot":242,"baitId":29714,"biteTime":5,"occurences":19},{"itemId":29769,"spot":242,"baitId":29714,"biteTime":5,"occurences":7},{"itemId":29772,"spot":242,"baitId":29714,"biteTime":5,"occurences":18},{"itemId":29774,"spot":242,"baitId":29714,"biteTime":5,"occurences":6},{"itemId":29780,"spot":242,"baitId":29714,"biteTime":5,"occurences":15},{"itemId":29769,"spot":242,"baitId":29714,"biteTime":5,"occurences":15},{"itemId":29772,"spot":242,"baitId":29714,"biteTime":5,"occurences":12},{"itemId":29774,"spot":242,"baitId":29714,"biteTime":5,"occurences":9},{"itemId":29780,"spot":242,"baitId":29714,"biteTime":5,"occurences":17},{"itemId":29769,"spot":242,"baitId":29714,"biteTime":5,"occurences":14},{"itemId":29772,"spot":242,"baitId":29714,"biteTime":5,"occurences":16},{"itemId":29774,"spot":242,"baitId":29714,"biteTime":5,"occurences":7},{"itemId":29780,"spot":242,"baitId":29714,"biteTime":5,"occurences":13},{"itemId":29769,"spot":242,"baitId":29714,"biteTime":5,"occurences":13},{"itemId":29772,"spot":242,"baitId":29714,"biteTime":5,"occurences":8},{"itemId":29774,"spot":242,"baitId":29714,"biteTime":5,"occurences":9},{"itemId":29780,"spot":242,"baitId":29714,"biteTime":5,"occurences":9},{"itemId":29769,"spot":242,"baitId":29714,"biteTime":5,"occurences":23},{"itemId":29772,"spot":242,"baitId":29714,"biteTime":5,"occurences":3},{"itemId":29774,"spot":242,"baitId":29714,"biteTime":5,"occurences":4},{"itemId":29780,"spot":242,"baitId":29714,"biteTime":5,"occurences":3},{"itemId":29769,"spot":242,"baitId":29714,"biteTime":5,"occurences":12},{"itemId":29772,"spot":242,"baitId":29714,"biteTime":5,"occurences":1},{"itemId":29780,"spot":242,"baitId":29714,"biteTime":5,"occurences":3},{"itemId":29769,"spot":242,"baitId":29714,"biteTime":5,"occurences":18},{"itemId":29772,"spot":242,"baitId":29714,"biteTime":5,"occurences":1},{"itemId":29769,"spot":242,"baitId":29714,"biteTime":6,"occurences":20},{"itemId":29769,"spot":242,"baitId":29714,"biteTime":6,"occurences":24},{"itemId":29769,"spot":242,"baitId":29714,"biteTime":6,"occurences":12},{"itemId":29769,"spot":242,"baitId":29714,"biteTime":6,"occurences":16},{"itemId":29767,"spot":242,"baitId":29714,"biteTime":6,"occurences":1},{"itemId":29769,"spot":242,"baitId":29714,"biteTime":6,"occurences":17},{"itemId":29774,"spot":242,"baitId":29714,"biteTime":6,"occurences":1},{"itemId":29767,"spot":242,"baitId":29714,"biteTime":6,"occurences":1},{"itemId":29769,"spot":242,"baitId":29714,"biteTime":6,"occurences":15},{"itemId":29767,"spot":242,"baitId":29714,"biteTime":6,"occurences":3},{"itemId":29769,"spot":242,"baitId":29714,"biteTime":6,"occurences":15},{"itemId":29767,"spot":242,"baitId":29714,"biteTime":6,"occurences":3},{"itemId":29769,"spot":242,"baitId":29714,"biteTime":6,"occurences":14},{"itemId":29770,"spot":242,"baitId":29714,"biteTime":6,"occurences":1},{"itemId":29767,"spot":242,"baitId":29714,"biteTime":6,"occurences":1},{"itemId":29769,"spot":242,"baitId":29714,"biteTime":6,"occurences":17},{"itemId":29767,"spot":242,"baitId":29714,"biteTime":6,"occurences":8},{"itemId":29769,"spot":242,"baitId":29714,"biteTime":6,"occurences":19},{"itemId":29769,"spot":242,"baitId":29714,"biteTime":7,"occurences":21},{"itemId":29767,"spot":242,"baitId":29714,"biteTime":7,"occurences":6},{"itemId":29769,"spot":242,"baitId":29714,"biteTime":7,"occurences":25},{"itemId":29770,"spot":242,"baitId":29714,"biteTime":7,"occurences":1},{"itemId":29767,"spot":242,"baitId":29714,"biteTime":7,"occurences":3},{"itemId":29769,"spot":242,"baitId":29714,"biteTime":7,"occurences":16},{"itemId":29767,"spot":242,"baitId":29714,"biteTime":7,"occurences":5},{"itemId":29769,"spot":242,"baitId":29714,"biteTime":7,"occurences":19},{"itemId":29770,"spot":242,"baitId":29714,"biteTime":7,"occurences":1},{"itemId":29767,"spot":242,"baitId":29714,"biteTime":7,"occurences":6},{"itemId":29769,"spot":242,"baitId":29714,"biteTime":7,"occurences":11},{"itemId":29780,"spot":242,"baitId":29714,"biteTime":7,"occurences":1},{"itemId":29767,"spot":242,"baitId":29714,"biteTime":7,"occurences":5},{"itemId":29769,"spot":242,"baitId":29714,"biteTime":7,"occurences":9},{"itemId":29769,"spot":242,"baitId":29714,"biteTime":7,"occurences":13},{"itemId":29769,"spot":242,"baitId":29714,"biteTime":7,"occurences":7},{"itemId":29769,"spot":242,"baitId":29714,"biteTime":7,"occurences":15},{"itemId":29769,"spot":242,"baitId":29714,"biteTime":7,"occurences":12},{"itemId":29780,"spot":242,"baitId":29714,"biteTime":7,"occurences":1},{"itemId":29767,"spot":242,"baitId":29714,"biteTime":8,"occurences":1},{"itemId":29769,"spot":242,"baitId":29714,"biteTime":8,"occurences":19},{"itemId":29770,"spot":242,"baitId":29714,"biteTime":8,"occurences":2},{"itemId":29769,"spot":242,"baitId":29714,"biteTime":8,"occurences":11},{"itemId":29769,"spot":242,"baitId":29714,"biteTime":8,"occurences":20},{"itemId":29769,"spot":242,"baitId":29714,"biteTime":8,"occurences":13},{"itemId":29769,"spot":242,"baitId":29714,"biteTime":8,"occurences":12},{"itemId":29769,"spot":242,"baitId":29714,"biteTime":8,"occurences":12},{"itemId":29769,"spot":242,"baitId":29714,"biteTime":8,"occurences":3},{"itemId":29769,"spot":242,"baitId":29714,"biteTime":8,"occurences":2},{"itemId":29769,"spot":242,"baitId":29714,"biteTime":8,"occurences":1},{"itemId":29769,"spot":242,"baitId":29714,"biteTime":8,"occurences":1},{"itemId":29775,"spot":242,"baitId":29714,"biteTime":15,"occurences":1},{"itemId":29780,"spot":242,"baitId":29714,"biteTime":97,"occurences":1},{"itemId":29768,"spot":242,"baitId":29715,"biteTime":2,"occurences":11},{"itemId":29775,"spot":242,"baitId":29715,"biteTime":2,"occurences":104},{"itemId":29768,"spot":242,"baitId":29715,"biteTime":2,"occurences":14},{"itemId":29775,"spot":242,"baitId":29715,"biteTime":2,"occurences":135},{"itemId":29780,"spot":242,"baitId":29715,"biteTime":2,"occurences":1},{"itemId":29768,"spot":242,"baitId":29715,"biteTime":2,"occurences":14},{"itemId":29775,"spot":242,"baitId":29715,"biteTime":2,"occurences":116},{"itemId":29780,"spot":242,"baitId":29715,"biteTime":2,"occurences":1},{"itemId":29768,"spot":242,"baitId":29715,"biteTime":2,"occurences":20},{"itemId":29775,"spot":242,"baitId":29715,"biteTime":2,"occurences":152},{"itemId":29768,"spot":242,"baitId":29715,"biteTime":2,"occurences":24},{"itemId":29772,"spot":242,"baitId":29715,"biteTime":2,"occurences":2},{"itemId":29775,"spot":242,"baitId":29715,"biteTime":2,"occurences":87},{"itemId":29780,"spot":242,"baitId":29715,"biteTime":2,"occurences":2},{"itemId":29768,"spot":242,"baitId":29715,"biteTime":2,"occurences":34},{"itemId":29772,"spot":242,"baitId":29715,"biteTime":2,"occurences":2},{"itemId":29775,"spot":242,"baitId":29715,"biteTime":2,"occurences":94},{"itemId":29780,"spot":242,"baitId":29715,"biteTime":2,"occurences":4},{"itemId":29768,"spot":242,"baitId":29715,"biteTime":2,"occurences":48},{"itemId":29772,"spot":242,"baitId":29715,"biteTime":2,"occurences":8},{"itemId":29775,"spot":242,"baitId":29715,"biteTime":2,"occurences":65},{"itemId":29780,"spot":242,"baitId":29715,"biteTime":2,"occurences":6},{"itemId":29768,"spot":242,"baitId":29715,"biteTime":2,"occurences":51},{"itemId":29772,"spot":242,"baitId":29715,"biteTime":2,"occurences":8},{"itemId":29775,"spot":242,"baitId":29715,"biteTime":2,"occurences":22},{"itemId":29780,"spot":242,"baitId":29715,"biteTime":2,"occurences":11},{"itemId":29768,"spot":242,"baitId":29715,"biteTime":2,"occurences":54},{"itemId":29772,"spot":242,"baitId":29715,"biteTime":2,"occurences":15},{"itemId":29775,"spot":242,"baitId":29715,"biteTime":2,"occurences":15},{"itemId":29780,"spot":242,"baitId":29715,"biteTime":2,"occurences":10},{"itemId":29768,"spot":242,"baitId":29715,"biteTime":2,"occurences":74},{"itemId":29772,"spot":242,"baitId":29715,"biteTime":2,"occurences":20},{"itemId":29775,"spot":242,"baitId":29715,"biteTime":2,"occurences":9},{"itemId":29780,"spot":242,"baitId":29715,"biteTime":2,"occurences":9},{"itemId":29768,"spot":242,"baitId":29715,"biteTime":3,"occurences":63},{"itemId":29772,"spot":242,"baitId":29715,"biteTime":3,"occurences":17},{"itemId":29775,"spot":242,"baitId":29715,"biteTime":3,"occurences":1},{"itemId":29780,"spot":242,"baitId":29715,"biteTime":3,"occurences":13},{"itemId":29768,"spot":242,"baitId":29715,"biteTime":3,"occurences":68},{"itemId":29772,"spot":242,"baitId":29715,"biteTime":3,"occurences":19},{"itemId":29775,"spot":242,"baitId":29715,"biteTime":3,"occurences":1},{"itemId":29780,"spot":242,"baitId":29715,"biteTime":3,"occurences":25},{"itemId":29768,"spot":242,"baitId":29715,"biteTime":3,"occurences":58},{"itemId":29772,"spot":242,"baitId":29715,"biteTime":3,"occurences":12},{"itemId":29780,"spot":242,"baitId":29715,"biteTime":3,"occurences":20},{"itemId":29768,"spot":242,"baitId":29715,"biteTime":3,"occurences":72},{"itemId":29772,"spot":242,"baitId":29715,"biteTime":3,"occurences":26},{"itemId":29780,"spot":242,"baitId":29715,"biteTime":3,"occurences":23},{"itemId":29768,"spot":242,"baitId":29715,"biteTime":3,"occurences":61},{"itemId":29772,"spot":242,"baitId":29715,"biteTime":3,"occurences":36},{"itemId":29780,"spot":242,"baitId":29715,"biteTime":3,"occurences":50},{"itemId":29768,"spot":242,"baitId":29715,"biteTime":3,"occurences":53},{"itemId":29772,"spot":242,"baitId":29715,"biteTime":3,"occurences":42},{"itemId":29780,"spot":242,"baitId":29715,"biteTime":3,"occurences":52},{"itemId":29768,"spot":242,"baitId":29715,"biteTime":3,"occurences":59},{"itemId":29772,"spot":242,"baitId":29715,"biteTime":3,"occurences":52},{"itemId":29780,"spot":242,"baitId":29715,"biteTime":3,"occurences":51},{"itemId":29768,"spot":242,"baitId":29715,"biteTime":3,"occurences":50},{"itemId":29772,"spot":242,"baitId":29715,"biteTime":3,"occurences":58},{"itemId":29780,"spot":242,"baitId":29715,"biteTime":3,"occurences":53},{"itemId":29768,"spot":242,"baitId":29715,"biteTime":3,"occurences":48},{"itemId":29772,"spot":242,"baitId":29715,"biteTime":3,"occurences":52},{"itemId":29780,"spot":242,"baitId":29715,"biteTime":3,"occurences":70},{"itemId":29768,"spot":242,"baitId":29715,"biteTime":3,"occurences":52},{"itemId":29769,"spot":242,"baitId":29715,"biteTime":3,"occurences":1},{"itemId":29772,"spot":242,"baitId":29715,"biteTime":3,"occurences":61},{"itemId":29780,"spot":242,"baitId":29715,"biteTime":3,"occurences":56},{"itemId":29768,"spot":242,"baitId":29715,"biteTime":4,"occurences":39},{"itemId":29769,"spot":242,"baitId":29715,"biteTime":4,"occurences":1},{"itemId":29772,"spot":242,"baitId":29715,"biteTime":4,"occurences":53},{"itemId":29780,"spot":242,"baitId":29715,"biteTime":4,"occurences":45},{"itemId":29768,"spot":242,"baitId":29715,"biteTime":4,"occurences":20},{"itemId":29769,"spot":242,"baitId":29715,"biteTime":4,"occurences":3},{"itemId":29772,"spot":242,"baitId":29715,"biteTime":4,"occurences":56},{"itemId":29780,"spot":242,"baitId":29715,"biteTime":4,"occurences":45},{"itemId":29768,"spot":242,"baitId":29715,"biteTime":4,"occurences":12},{"itemId":29769,"spot":242,"baitId":29715,"biteTime":4,"occurences":7},{"itemId":29772,"spot":242,"baitId":29715,"biteTime":4,"occurences":64},{"itemId":29780,"spot":242,"baitId":29715,"biteTime":4,"occurences":49},{"itemId":29768,"spot":242,"baitId":29715,"biteTime":4,"occurences":6},{"itemId":29769,"spot":242,"baitId":29715,"biteTime":4,"occurences":2},{"itemId":29772,"spot":242,"baitId":29715,"biteTime":4,"occurences":67},{"itemId":29780,"spot":242,"baitId":29715,"biteTime":4,"occurences":58},{"itemId":29768,"spot":242,"baitId":29715,"biteTime":4,"occurences":2},{"itemId":29769,"spot":242,"baitId":29715,"biteTime":4,"occurences":7},{"itemId":29772,"spot":242,"baitId":29715,"biteTime":4,"occurences":61},{"itemId":29780,"spot":242,"baitId":29715,"biteTime":4,"occurences":53},{"itemId":29768,"spot":242,"baitId":29715,"biteTime":4,"occurences":1},{"itemId":29769,"spot":242,"baitId":29715,"biteTime":4,"occurences":5},{"itemId":29772,"spot":242,"baitId":29715,"biteTime":4,"occurences":52},{"itemId":29780,"spot":242,"baitId":29715,"biteTime":4,"occurences":56},{"itemId":29769,"spot":242,"baitId":29715,"biteTime":4,"occurences":7},{"itemId":29772,"spot":242,"baitId":29715,"biteTime":4,"occurences":53},{"itemId":29780,"spot":242,"baitId":29715,"biteTime":4,"occurences":57},{"itemId":29769,"spot":242,"baitId":29715,"biteTime":4,"occurences":4},{"itemId":29772,"spot":242,"baitId":29715,"biteTime":4,"occurences":42},{"itemId":29775,"spot":242,"baitId":29715,"biteTime":4,"occurences":1},{"itemId":29780,"spot":242,"baitId":29715,"biteTime":4,"occurences":71},{"itemId":29769,"spot":242,"baitId":29715,"biteTime":4,"occurences":14},{"itemId":29772,"spot":242,"baitId":29715,"biteTime":4,"occurences":59},{"itemId":29780,"spot":242,"baitId":29715,"biteTime":4,"occurences":44},{"itemId":29769,"spot":242,"baitId":29715,"biteTime":4,"occurences":16},{"itemId":29772,"spot":242,"baitId":29715,"biteTime":4,"occurences":53},{"itemId":29780,"spot":242,"baitId":29715,"biteTime":4,"occurences":64},{"itemId":29769,"spot":242,"baitId":29715,"biteTime":5,"occurences":17},{"itemId":29772,"spot":242,"baitId":29715,"biteTime":5,"occurences":43},{"itemId":29780,"spot":242,"baitId":29715,"biteTime":5,"occurences":44},{"itemId":29769,"spot":242,"baitId":29715,"biteTime":5,"occurences":21},{"itemId":29772,"spot":242,"baitId":29715,"biteTime":5,"occurences":41},{"itemId":29780,"spot":242,"baitId":29715,"biteTime":5,"occurences":48},{"itemId":29769,"spot":242,"baitId":29715,"biteTime":5,"occurences":26},{"itemId":29772,"spot":242,"baitId":29715,"biteTime":5,"occurences":50},{"itemId":29780,"spot":242,"baitId":29715,"biteTime":5,"occurences":45},{"itemId":29769,"spot":242,"baitId":29715,"biteTime":5,"occurences":14},{"itemId":29772,"spot":242,"baitId":29715,"biteTime":5,"occurences":37},{"itemId":29780,"spot":242,"baitId":29715,"biteTime":5,"occurences":29},{"itemId":29769,"spot":242,"baitId":29715,"biteTime":5,"occurences":19},{"itemId":29772,"spot":242,"baitId":29715,"biteTime":5,"occurences":40},{"itemId":29780,"spot":242,"baitId":29715,"biteTime":5,"occurences":47},{"itemId":29762,"spot":242,"baitId":29715,"biteTime":5,"occurences":1},{"itemId":29769,"spot":242,"baitId":29715,"biteTime":5,"occurences":26},{"itemId":29772,"spot":242,"baitId":29715,"biteTime":5,"occurences":26},{"itemId":29780,"spot":242,"baitId":29715,"biteTime":5,"occurences":34},{"itemId":29769,"spot":242,"baitId":29715,"biteTime":5,"occurences":21},{"itemId":29772,"spot":242,"baitId":29715,"biteTime":5,"occurences":19},{"itemId":29780,"spot":242,"baitId":29715,"biteTime":5,"occurences":18},{"itemId":29769,"spot":242,"baitId":29715,"biteTime":5,"occurences":26},{"itemId":29772,"spot":242,"baitId":29715,"biteTime":5,"occurences":8},{"itemId":29780,"spot":242,"baitId":29715,"biteTime":5,"occurences":7},{"itemId":29769,"spot":242,"baitId":29715,"biteTime":5,"occurences":14},{"itemId":29772,"spot":242,"baitId":29715,"biteTime":5,"occurences":1},{"itemId":29780,"spot":242,"baitId":29715,"biteTime":5,"occurences":4},{"itemId":29769,"spot":242,"baitId":29715,"biteTime":5,"occurences":23},{"itemId":29772,"spot":242,"baitId":29715,"biteTime":5,"occurences":2},{"itemId":29780,"spot":242,"baitId":29715,"biteTime":5,"occurences":3},{"itemId":29769,"spot":242,"baitId":29715,"biteTime":6,"occurences":16},{"itemId":29769,"spot":242,"baitId":29715,"biteTime":6,"occurences":16},{"itemId":29762,"spot":242,"baitId":29715,"biteTime":6,"occurences":3},{"itemId":29769,"spot":242,"baitId":29715,"biteTime":6,"occurences":25},{"itemId":29769,"spot":242,"baitId":29715,"biteTime":6,"occurences":18},{"itemId":29762,"spot":242,"baitId":29715,"biteTime":6,"occurences":2},{"itemId":29769,"spot":242,"baitId":29715,"biteTime":6,"occurences":24},{"itemId":29772,"spot":242,"baitId":29715,"biteTime":6,"occurences":1},{"itemId":29762,"spot":242,"baitId":29715,"biteTime":6,"occurences":6},{"itemId":29769,"spot":242,"baitId":29715,"biteTime":6,"occurences":18},{"itemId":29762,"spot":242,"baitId":29715,"biteTime":6,"occurences":6},{"itemId":29769,"spot":242,"baitId":29715,"biteTime":6,"occurences":18},{"itemId":29762,"spot":242,"baitId":29715,"biteTime":6,"occurences":6},{"itemId":29769,"spot":242,"baitId":29715,"biteTime":6,"occurences":16},{"itemId":29762,"spot":242,"baitId":29715,"biteTime":6,"occurences":6},{"itemId":29769,"spot":242,"baitId":29715,"biteTime":6,"occurences":20},{"itemId":29762,"spot":242,"baitId":29715,"biteTime":6,"occurences":4},{"itemId":29769,"spot":242,"baitId":29715,"biteTime":6,"occurences":22},{"itemId":29762,"spot":242,"baitId":29715,"biteTime":7,"occurences":6},{"itemId":29769,"spot":242,"baitId":29715,"biteTime":7,"occurences":16},{"itemId":29780,"spot":242,"baitId":29715,"biteTime":7,"occurences":1},{"itemId":29762,"spot":242,"baitId":29715,"biteTime":7,"occurences":11},{"itemId":29769,"spot":242,"baitId":29715,"biteTime":7,"occurences":21},{"itemId":29762,"spot":242,"baitId":29715,"biteTime":7,"occurences":15},{"itemId":29769,"spot":242,"baitId":29715,"biteTime":7,"occurences":19},{"itemId":29762,"spot":242,"baitId":29715,"biteTime":7,"occurences":14},{"itemId":29769,"spot":242,"baitId":29715,"biteTime":7,"occurences":14},{"itemId":29762,"spot":242,"baitId":29715,"biteTime":7,"occurences":15},{"itemId":29769,"spot":242,"baitId":29715,"biteTime":7,"occurences":21},{"itemId":29762,"spot":242,"baitId":29715,"biteTime":7,"occurences":10},{"itemId":29769,"spot":242,"baitId":29715,"biteTime":7,"occurences":21},{"itemId":29762,"spot":242,"baitId":29715,"biteTime":7,"occurences":14},{"itemId":29769,"spot":242,"baitId":29715,"biteTime":7,"occurences":18},{"itemId":29780,"spot":242,"baitId":29715,"biteTime":7,"occurences":1},{"itemId":29762,"spot":242,"baitId":29715,"biteTime":7,"occurences":18},{"itemId":29769,"spot":242,"baitId":29715,"biteTime":7,"occurences":17},{"itemId":29762,"spot":242,"baitId":29715,"biteTime":7,"occurences":11},{"itemId":29769,"spot":242,"baitId":29715,"biteTime":7,"occurences":24},{"itemId":29762,"spot":242,"baitId":29715,"biteTime":7,"occurences":15},{"itemId":29769,"spot":242,"baitId":29715,"biteTime":7,"occurences":14},{"itemId":29762,"spot":242,"baitId":29715,"biteTime":8,"occurences":15},{"itemId":29769,"spot":242,"baitId":29715,"biteTime":8,"occurences":12},{"itemId":29762,"spot":242,"baitId":29715,"biteTime":8,"occurences":21},{"itemId":29769,"spot":242,"baitId":29715,"biteTime":8,"occurences":18},{"itemId":29762,"spot":242,"baitId":29715,"biteTime":8,"occurences":22},{"itemId":29769,"spot":242,"baitId":29715,"biteTime":8,"occurences":13},{"itemId":29762,"spot":242,"baitId":29715,"biteTime":8,"occurences":13},{"itemId":29769,"spot":242,"baitId":29715,"biteTime":8,"occurences":24},{"itemId":29762,"spot":242,"baitId":29715,"biteTime":8,"occurences":20},{"itemId":29769,"spot":242,"baitId":29715,"biteTime":8,"occurences":16},{"itemId":29762,"spot":242,"baitId":29715,"biteTime":8,"occurences":12},{"itemId":29769,"spot":242,"baitId":29715,"biteTime":8,"occurences":17},{"itemId":29762,"spot":242,"baitId":29715,"biteTime":8,"occurences":12},{"itemId":29769,"spot":242,"baitId":29715,"biteTime":8,"occurences":9},{"itemId":29762,"spot":242,"baitId":29715,"biteTime":8,"occurences":11},{"itemId":29769,"spot":242,"baitId":29715,"biteTime":8,"occurences":1},{"itemId":29762,"spot":242,"baitId":29715,"biteTime":8,"occurences":21},{"itemId":29769,"spot":242,"baitId":29715,"biteTime":8,"occurences":3},{"itemId":29762,"spot":242,"baitId":29715,"biteTime":8,"occurences":13},{"itemId":29762,"spot":242,"baitId":29715,"biteTime":9,"occurences":16},{"itemId":29762,"spot":242,"baitId":29715,"biteTime":9,"occurences":9},{"itemId":29762,"spot":242,"baitId":29715,"biteTime":9,"occurences":8},{"itemId":29762,"spot":242,"baitId":29715,"biteTime":9,"occurences":16},{"itemId":29762,"spot":242,"baitId":29715,"biteTime":9,"occurences":10},{"itemId":29762,"spot":242,"baitId":29715,"biteTime":9,"occurences":11},{"itemId":29762,"spot":242,"baitId":29715,"biteTime":9,"occurences":11},{"itemId":29762,"spot":242,"baitId":29715,"biteTime":9,"occurences":7},{"itemId":29762,"spot":242,"baitId":29715,"biteTime":9,"occurences":4},{"itemId":29762,"spot":242,"baitId":29715,"biteTime":9,"occurences":4},{"itemId":29762,"spot":242,"baitId":29715,"biteTime":10,"occurences":7},{"itemId":29762,"spot":242,"baitId":29715,"biteTime":10,"occurences":4},{"itemId":29762,"spot":242,"baitId":29715,"biteTime":10,"occurences":3},{"itemId":29775,"spot":242,"baitId":29715,"biteTime":12,"occurences":1},{"itemId":29780,"spot":242,"baitId":29715,"biteTime":12,"occurences":1},{"itemId":29769,"spot":242,"baitId":29715,"biteTime":12,"occurences":1},{"itemId":29762,"spot":242,"baitId":29715,"biteTime":12,"occurences":1},{"itemId":29769,"spot":242,"baitId":29715,"biteTime":13,"occurences":1},{"itemId":29762,"spot":242,"baitId":29715,"biteTime":18,"occurences":1},{"itemId":29762,"spot":242,"baitId":29715,"biteTime":20,"occurences":1},{"itemId":29780,"spot":242,"baitId":29715,"biteTime":22,"occurences":1},{"itemId":29768,"spot":242,"baitId":29716,"biteTime":2,"occurences":21},{"itemId":29772,"spot":242,"baitId":29716,"biteTime":2,"occurences":1},{"itemId":29775,"spot":242,"baitId":29716,"biteTime":2,"occurences":375},{"itemId":29780,"spot":242,"baitId":29716,"biteTime":2,"occurences":1},{"itemId":29768,"spot":242,"baitId":29716,"biteTime":2,"occurences":21},{"itemId":29772,"spot":242,"baitId":29716,"biteTime":2,"occurences":1},{"itemId":29775,"spot":242,"baitId":29716,"biteTime":2,"occurences":372},{"itemId":29780,"spot":242,"baitId":29716,"biteTime":2,"occurences":1},{"itemId":29768,"spot":242,"baitId":29716,"biteTime":2,"occurences":21},{"itemId":29775,"spot":242,"baitId":29716,"biteTime":2,"occurences":402},{"itemId":29780,"spot":242,"baitId":29716,"biteTime":2,"occurences":2},{"itemId":29768,"spot":242,"baitId":29716,"biteTime":2,"occurences":35},{"itemId":29772,"spot":242,"baitId":29716,"biteTime":2,"occurences":6},{"itemId":29775,"spot":242,"baitId":29716,"biteTime":2,"occurences":414},{"itemId":29780,"spot":242,"baitId":29716,"biteTime":2,"occurences":3},{"itemId":29768,"spot":242,"baitId":29716,"biteTime":2,"occurences":47},{"itemId":29769,"spot":242,"baitId":29716,"biteTime":2,"occurences":1},{"itemId":29772,"spot":242,"baitId":29716,"biteTime":2,"occurences":5},{"itemId":29775,"spot":242,"baitId":29716,"biteTime":2,"occurences":360},{"itemId":29780,"spot":242,"baitId":29716,"biteTime":2,"occurences":6},{"itemId":29768,"spot":242,"baitId":29716,"biteTime":2,"occurences":66},{"itemId":29772,"spot":242,"baitId":29716,"biteTime":2,"occurences":4},{"itemId":29775,"spot":242,"baitId":29716,"biteTime":2,"occurences":307},{"itemId":29780,"spot":242,"baitId":29716,"biteTime":2,"occurences":8},{"itemId":29767,"spot":242,"baitId":29716,"biteTime":2,"occurences":1},{"itemId":29768,"spot":242,"baitId":29716,"biteTime":2,"occurences":110},{"itemId":29772,"spot":242,"baitId":29716,"biteTime":2,"occurences":8},{"itemId":29775,"spot":242,"baitId":29716,"biteTime":2,"occurences":198},{"itemId":29780,"spot":242,"baitId":29716,"biteTime":2,"occurences":9},{"itemId":29768,"spot":242,"baitId":29716,"biteTime":2,"occurences":161},{"itemId":29772,"spot":242,"baitId":29716,"biteTime":2,"occurences":15},{"itemId":29775,"spot":242,"baitId":29716,"biteTime":2,"occurences":88},{"itemId":29780,"spot":242,"baitId":29716,"biteTime":2,"occurences":13},{"itemId":29767,"spot":242,"baitId":29716,"biteTime":2,"occurences":1},{"itemId":29768,"spot":242,"baitId":29716,"biteTime":2,"occurences":173},{"itemId":29769,"spot":242,"baitId":29716,"biteTime":2,"occurences":1},{"itemId":29772,"spot":242,"baitId":29716,"biteTime":2,"occurences":14},{"itemId":29775,"spot":242,"baitId":29716,"biteTime":2,"occurences":43},{"itemId":29780,"spot":242,"baitId":29716,"biteTime":2,"occurences":24},{"itemId":29768,"spot":242,"baitId":29716,"biteTime":2,"occurences":162},{"itemId":29772,"spot":242,"baitId":29716,"biteTime":2,"occurences":33},{"itemId":29775,"spot":242,"baitId":29716,"biteTime":2,"occurences":11},{"itemId":29780,"spot":242,"baitId":29716,"biteTime":2,"occurences":31},{"itemId":29768,"spot":242,"baitId":29716,"biteTime":3,"occurences":200},{"itemId":29769,"spot":242,"baitId":29716,"biteTime":3,"occurences":1},{"itemId":29772,"spot":242,"baitId":29716,"biteTime":3,"occurences":24},{"itemId":29775,"spot":242,"baitId":29716,"biteTime":3,"occurences":3},{"itemId":29780,"spot":242,"baitId":29716,"biteTime":3,"occurences":32},{"itemId":29768,"spot":242,"baitId":29716,"biteTime":3,"occurences":171},{"itemId":29769,"spot":242,"baitId":29716,"biteTime":3,"occurences":1},{"itemId":29772,"spot":242,"baitId":29716,"biteTime":3,"occurences":27},{"itemId":29775,"spot":242,"baitId":29716,"biteTime":3,"occurences":2},{"itemId":29780,"spot":242,"baitId":29716,"biteTime":3,"occurences":25},{"itemId":29767,"spot":242,"baitId":29716,"biteTime":3,"occurences":1},{"itemId":29768,"spot":242,"baitId":29716,"biteTime":3,"occurences":200},{"itemId":29769,"spot":242,"baitId":29716,"biteTime":3,"occurences":1},{"itemId":29772,"spot":242,"baitId":29716,"biteTime":3,"occurences":35},{"itemId":29780,"spot":242,"baitId":29716,"biteTime":3,"occurences":41},{"itemId":29768,"spot":242,"baitId":29716,"biteTime":3,"occurences":226},{"itemId":29772,"spot":242,"baitId":29716,"biteTime":3,"occurences":46},{"itemId":29780,"spot":242,"baitId":29716,"biteTime":3,"occurences":58},{"itemId":29767,"spot":242,"baitId":29716,"biteTime":3,"occurences":1},{"itemId":29768,"spot":242,"baitId":29716,"biteTime":3,"occurences":170},{"itemId":29772,"spot":242,"baitId":29716,"biteTime":3,"occurences":106},{"itemId":29780,"spot":242,"baitId":29716,"biteTime":3,"occurences":89},{"itemId":29767,"spot":242,"baitId":29716,"biteTime":3,"occurences":2},{"itemId":29768,"spot":242,"baitId":29716,"biteTime":3,"occurences":176},{"itemId":29769,"spot":242,"baitId":29716,"biteTime":3,"occurences":3},{"itemId":29772,"spot":242,"baitId":29716,"biteTime":3,"occurences":113},{"itemId":29775,"spot":242,"baitId":29716,"biteTime":3,"occurences":1},{"itemId":29780,"spot":242,"baitId":29716,"biteTime":3,"occurences":120},{"itemId":29767,"spot":242,"baitId":29716,"biteTime":3,"occurences":1},{"itemId":29768,"spot":242,"baitId":29716,"biteTime":3,"occurences":167},{"itemId":29770,"spot":242,"baitId":29716,"biteTime":3,"occurences":1},{"itemId":29772,"spot":242,"baitId":29716,"biteTime":3,"occurences":139},{"itemId":29775,"spot":242,"baitId":29716,"biteTime":3,"occurences":1},{"itemId":29780,"spot":242,"baitId":29716,"biteTime":3,"occurences":125},{"itemId":29768,"spot":242,"baitId":29716,"biteTime":3,"occurences":132},{"itemId":29769,"spot":242,"baitId":29716,"biteTime":3,"occurences":1},{"itemId":29772,"spot":242,"baitId":29716,"biteTime":3,"occurences":117},{"itemId":29775,"spot":242,"baitId":29716,"biteTime":3,"occurences":2},{"itemId":29780,"spot":242,"baitId":29716,"biteTime":3,"occurences":99},{"itemId":29767,"spot":242,"baitId":29716,"biteTime":3,"occurences":2},{"itemId":29768,"spot":242,"baitId":29716,"biteTime":3,"occurences":168},{"itemId":29769,"spot":242,"baitId":29716,"biteTime":3,"occurences":2},{"itemId":29772,"spot":242,"baitId":29716,"biteTime":3,"occurences":138},{"itemId":29780,"spot":242,"baitId":29716,"biteTime":3,"occurences":115},{"itemId":29767,"spot":242,"baitId":29716,"biteTime":3,"occurences":2},{"itemId":29768,"spot":242,"baitId":29716,"biteTime":3,"occurences":133},{"itemId":29769,"spot":242,"baitId":29716,"biteTime":3,"occurences":6},{"itemId":29772,"spot":242,"baitId":29716,"biteTime":3,"occurences":131},{"itemId":29780,"spot":242,"baitId":29716,"biteTime":3,"occurences":124},{"itemId":29767,"spot":242,"baitId":29716,"biteTime":4,"occurences":4},{"itemId":29768,"spot":242,"baitId":29716,"biteTime":4,"occurences":99},{"itemId":29769,"spot":242,"baitId":29716,"biteTime":4,"occurences":7},{"itemId":29772,"spot":242,"baitId":29716,"biteTime":4,"occurences":118},{"itemId":29780,"spot":242,"baitId":29716,"biteTime":4,"occurences":118},{"itemId":29767,"spot":242,"baitId":29716,"biteTime":4,"occurences":11},{"itemId":29768,"spot":242,"baitId":29716,"biteTime":4,"occurences":60},{"itemId":29769,"spot":242,"baitId":29716,"biteTime":4,"occurences":9},{"itemId":29772,"spot":242,"baitId":29716,"biteTime":4,"occurences":115},{"itemId":29780,"spot":242,"baitId":29716,"biteTime":4,"occurences":118},{"itemId":29767,"spot":242,"baitId":29716,"biteTime":4,"occurences":17},{"itemId":29768,"spot":242,"baitId":29716,"biteTime":4,"occurences":26},{"itemId":29769,"spot":242,"baitId":29716,"biteTime":4,"occurences":9},{"itemId":29772,"spot":242,"baitId":29716,"biteTime":4,"occurences":138},{"itemId":29780,"spot":242,"baitId":29716,"biteTime":4,"occurences":122},{"itemId":29767,"spot":242,"baitId":29716,"biteTime":4,"occurences":21},{"itemId":29768,"spot":242,"baitId":29716,"biteTime":4,"occurences":8},{"itemId":29769,"spot":242,"baitId":29716,"biteTime":4,"occurences":17},{"itemId":29772,"spot":242,"baitId":29716,"biteTime":4,"occurences":129},{"itemId":29780,"spot":242,"baitId":29716,"biteTime":4,"occurences":162},{"itemId":29767,"spot":242,"baitId":29716,"biteTime":4,"occurences":21},{"itemId":29768,"spot":242,"baitId":29716,"biteTime":4,"occurences":4},{"itemId":29769,"spot":242,"baitId":29716,"biteTime":4,"occurences":14},{"itemId":29772,"spot":242,"baitId":29716,"biteTime":4,"occurences":161},{"itemId":29780,"spot":242,"baitId":29716,"biteTime":4,"occurences":145},{"itemId":29767,"spot":242,"baitId":29716,"biteTime":4,"occurences":31},{"itemId":29768,"spot":242,"baitId":29716,"biteTime":4,"occurences":1},{"itemId":29769,"spot":242,"baitId":29716,"biteTime":4,"occurences":27},{"itemId":29772,"spot":242,"baitId":29716,"biteTime":4,"occurences":132},{"itemId":29780,"spot":242,"baitId":29716,"biteTime":4,"occurences":114},{"itemId":29767,"spot":242,"baitId":29716,"biteTime":4,"occurences":28},{"itemId":29769,"spot":242,"baitId":29716,"biteTime":4,"occurences":39},{"itemId":29772,"spot":242,"baitId":29716,"biteTime":4,"occurences":124},{"itemId":29780,"spot":242,"baitId":29716,"biteTime":4,"occurences":143},{"itemId":29767,"spot":242,"baitId":29716,"biteTime":4,"occurences":32},{"itemId":29768,"spot":242,"baitId":29716,"biteTime":4,"occurences":1},{"itemId":29769,"spot":242,"baitId":29716,"biteTime":4,"occurences":38},{"itemId":29770,"spot":242,"baitId":29716,"biteTime":4,"occurences":2},{"itemId":29772,"spot":242,"baitId":29716,"biteTime":4,"occurences":108},{"itemId":29780,"spot":242,"baitId":29716,"biteTime":4,"occurences":135},{"itemId":29767,"spot":242,"baitId":29716,"biteTime":4,"occurences":42},{"itemId":29769,"spot":242,"baitId":29716,"biteTime":4,"occurences":76},{"itemId":29772,"spot":242,"baitId":29716,"biteTime":4,"occurences":129},{"itemId":29780,"spot":242,"baitId":29716,"biteTime":4,"occurences":106},{"itemId":29767,"spot":242,"baitId":29716,"biteTime":4,"occurences":69},{"itemId":29768,"spot":242,"baitId":29716,"biteTime":4,"occurences":1},{"itemId":29769,"spot":242,"baitId":29716,"biteTime":4,"occurences":103},{"itemId":29772,"spot":242,"baitId":29716,"biteTime":4,"occurences":136},{"itemId":29780,"spot":242,"baitId":29716,"biteTime":4,"occurences":115},{"itemId":29767,"spot":242,"baitId":29716,"biteTime":5,"occurences":93},{"itemId":29769,"spot":242,"baitId":29716,"biteTime":5,"occurences":114},{"itemId":29772,"spot":242,"baitId":29716,"biteTime":5,"occurences":116},{"itemId":29780,"spot":242,"baitId":29716,"biteTime":5,"occurences":106},{"itemId":29767,"spot":242,"baitId":29716,"biteTime":5,"occurences":113},{"itemId":29769,"spot":242,"baitId":29716,"biteTime":5,"occurences":120},{"itemId":29772,"spot":242,"baitId":29716,"biteTime":5,"occurences":98},{"itemId":29780,"spot":242,"baitId":29716,"biteTime":5,"occurences":109},{"itemId":29767,"spot":242,"baitId":29716,"biteTime":5,"occurences":103},{"itemId":29769,"spot":242,"baitId":29716,"biteTime":5,"occurences":117},{"itemId":29772,"spot":242,"baitId":29716,"biteTime":5,"occurences":122},{"itemId":29780,"spot":242,"baitId":29716,"biteTime":5,"occurences":93},{"itemId":29767,"spot":242,"baitId":29716,"biteTime":5,"occurences":102},{"itemId":29769,"spot":242,"baitId":29716,"biteTime":5,"occurences":141},{"itemId":29772,"spot":242,"baitId":29716,"biteTime":5,"occurences":97},{"itemId":29780,"spot":242,"baitId":29716,"biteTime":5,"occurences":103},{"itemId":29767,"spot":242,"baitId":29716,"biteTime":5,"occurences":99},{"itemId":29769,"spot":242,"baitId":29716,"biteTime":5,"occurences":142},{"itemId":29770,"spot":242,"baitId":29716,"biteTime":5,"occurences":3},{"itemId":29772,"spot":242,"baitId":29716,"biteTime":5,"occurences":95},{"itemId":29780,"spot":242,"baitId":29716,"biteTime":5,"occurences":84},{"itemId":29767,"spot":242,"baitId":29716,"biteTime":5,"occurences":92},{"itemId":29769,"spot":242,"baitId":29716,"biteTime":5,"occurences":137},{"itemId":29770,"spot":242,"baitId":29716,"biteTime":5,"occurences":4},{"itemId":29772,"spot":242,"baitId":29716,"biteTime":5,"occurences":75},{"itemId":29780,"spot":242,"baitId":29716,"biteTime":5,"occurences":86},{"itemId":29767,"spot":242,"baitId":29716,"biteTime":5,"occurences":52},{"itemId":29769,"spot":242,"baitId":29716,"biteTime":5,"occurences":133},{"itemId":29770,"spot":242,"baitId":29716,"biteTime":5,"occurences":4},{"itemId":29772,"spot":242,"baitId":29716,"biteTime":5,"occurences":50},{"itemId":29780,"spot":242,"baitId":29716,"biteTime":5,"occurences":49},{"itemId":29767,"spot":242,"baitId":29716,"biteTime":5,"occurences":20},{"itemId":29769,"spot":242,"baitId":29716,"biteTime":5,"occurences":143},{"itemId":29770,"spot":242,"baitId":29716,"biteTime":5,"occurences":5},{"itemId":29772,"spot":242,"baitId":29716,"biteTime":5,"occurences":17},{"itemId":29780,"spot":242,"baitId":29716,"biteTime":5,"occurences":19},{"itemId":29767,"spot":242,"baitId":29716,"biteTime":5,"occurences":12},{"itemId":29769,"spot":242,"baitId":29716,"biteTime":5,"occurences":116},{"itemId":29770,"spot":242,"baitId":29716,"biteTime":5,"occurences":10},{"itemId":29772,"spot":242,"baitId":29716,"biteTime":5,"occurences":8},{"itemId":29780,"spot":242,"baitId":29716,"biteTime":5,"occurences":13},{"itemId":29768,"spot":242,"baitId":29716,"biteTime":5,"occurences":1},{"itemId":29769,"spot":242,"baitId":29716,"biteTime":5,"occurences":118},{"itemId":29770,"spot":242,"baitId":29716,"biteTime":5,"occurences":13},{"itemId":29772,"spot":242,"baitId":29716,"biteTime":5,"occurences":4},{"itemId":29780,"spot":242,"baitId":29716,"biteTime":5,"occurences":1},{"itemId":29767,"spot":242,"baitId":29716,"biteTime":6,"occurences":2},{"itemId":29769,"spot":242,"baitId":29716,"biteTime":6,"occurences":119},{"itemId":29770,"spot":242,"baitId":29716,"biteTime":6,"occurences":8},{"itemId":29772,"spot":242,"baitId":29716,"biteTime":6,"occurences":2},{"itemId":29780,"spot":242,"baitId":29716,"biteTime":6,"occurences":1},{"itemId":29769,"spot":242,"baitId":29716,"biteTime":6,"occurences":145},{"itemId":29770,"spot":242,"baitId":29716,"biteTime":6,"occurences":13},{"itemId":29767,"spot":242,"baitId":29716,"biteTime":6,"occurences":1},{"itemId":29769,"spot":242,"baitId":29716,"biteTime":6,"occurences":136},{"itemId":29770,"spot":242,"baitId":29716,"biteTime":6,"occurences":16},{"itemId":29772,"spot":242,"baitId":29716,"biteTime":6,"occurences":1},{"itemId":29769,"spot":242,"baitId":29716,"biteTime":6,"occurences":124},{"itemId":29770,"spot":242,"baitId":29716,"biteTime":6,"occurences":24},{"itemId":29772,"spot":242,"baitId":29716,"biteTime":6,"occurences":1},{"itemId":29769,"spot":242,"baitId":29716,"biteTime":6,"occurences":132},{"itemId":29770,"spot":242,"baitId":29716,"biteTime":6,"occurences":37},{"itemId":29769,"spot":242,"baitId":29716,"biteTime":6,"occurences":144},{"itemId":29770,"spot":242,"baitId":29716,"biteTime":6,"occurences":47},{"itemId":29769,"spot":242,"baitId":29716,"biteTime":6,"occurences":136},{"itemId":29770,"spot":242,"baitId":29716,"biteTime":6,"occurences":54},{"itemId":29769,"spot":242,"baitId":29716,"biteTime":6,"occurences":146},{"itemId":29770,"spot":242,"baitId":29716,"biteTime":6,"occurences":50},{"itemId":29769,"spot":242,"baitId":29716,"biteTime":6,"occurences":127},{"itemId":29770,"spot":242,"baitId":29716,"biteTime":6,"occurences":51},{"itemId":29768,"spot":242,"baitId":29716,"biteTime":6,"occurences":1},{"itemId":29769,"spot":242,"baitId":29716,"biteTime":6,"occurences":121},{"itemId":29770,"spot":242,"baitId":29716,"biteTime":6,"occurences":60},{"itemId":29769,"spot":242,"baitId":29716,"biteTime":7,"occurences":132},{"itemId":29770,"spot":242,"baitId":29716,"biteTime":7,"occurences":48},{"itemId":29769,"spot":242,"baitId":29716,"biteTime":7,"occurences":106},{"itemId":29770,"spot":242,"baitId":29716,"biteTime":7,"occurences":41},{"itemId":29769,"spot":242,"baitId":29716,"biteTime":7,"occurences":142},{"itemId":29770,"spot":242,"baitId":29716,"biteTime":7,"occurences":36},{"itemId":29769,"spot":242,"baitId":29716,"biteTime":7,"occurences":143},{"itemId":29770,"spot":242,"baitId":29716,"biteTime":7,"occurences":46},{"itemId":29769,"spot":242,"baitId":29716,"biteTime":7,"occurences":137},{"itemId":29770,"spot":242,"baitId":29716,"biteTime":7,"occurences":44},{"itemId":29769,"spot":242,"baitId":29716,"biteTime":7,"occurences":139},{"itemId":29770,"spot":242,"baitId":29716,"biteTime":7,"occurences":52},{"itemId":29769,"spot":242,"baitId":29716,"biteTime":7,"occurences":152},{"itemId":29770,"spot":242,"baitId":29716,"biteTime":7,"occurences":51},{"itemId":29769,"spot":242,"baitId":29716,"biteTime":7,"occurences":111},{"itemId":29770,"spot":242,"baitId":29716,"biteTime":7,"occurences":37},{"itemId":29769,"spot":242,"baitId":29716,"biteTime":7,"occurences":124},{"itemId":29770,"spot":242,"baitId":29716,"biteTime":7,"occurences":38},{"itemId":29769,"spot":242,"baitId":29716,"biteTime":7,"occurences":142},{"itemId":29770,"spot":242,"baitId":29716,"biteTime":7,"occurences":35},{"itemId":29769,"spot":242,"baitId":29716,"biteTime":8,"occurences":138},{"itemId":29770,"spot":242,"baitId":29716,"biteTime":8,"occurences":50},{"itemId":29769,"spot":242,"baitId":29716,"biteTime":8,"occurences":93},{"itemId":29770,"spot":242,"baitId":29716,"biteTime":8,"occurences":32},{"itemId":29780,"spot":242,"baitId":29716,"biteTime":8,"occurences":1},{"itemId":29769,"spot":242,"baitId":29716,"biteTime":8,"occurences":95},{"itemId":29770,"spot":242,"baitId":29716,"biteTime":8,"occurences":56},{"itemId":29769,"spot":242,"baitId":29716,"biteTime":8,"occurences":109},{"itemId":29770,"spot":242,"baitId":29716,"biteTime":8,"occurences":40},{"itemId":29769,"spot":242,"baitId":29716,"biteTime":8,"occurences":108},{"itemId":29770,"spot":242,"baitId":29716,"biteTime":8,"occurences":31},{"itemId":29769,"spot":242,"baitId":29716,"biteTime":8,"occurences":58},{"itemId":29770,"spot":242,"baitId":29716,"biteTime":8,"occurences":26},{"itemId":29775,"spot":242,"baitId":29716,"biteTime":8,"occurences":1},{"itemId":29769,"spot":242,"baitId":29716,"biteTime":8,"occurences":40},{"itemId":29770,"spot":242,"baitId":29716,"biteTime":8,"occurences":12},{"itemId":29769,"spot":242,"baitId":29716,"biteTime":8,"occurences":32},{"itemId":29770,"spot":242,"baitId":29716,"biteTime":8,"occurences":5},{"itemId":29769,"spot":242,"baitId":29716,"biteTime":8,"occurences":14},{"itemId":29770,"spot":242,"baitId":29716,"biteTime":8,"occurences":2},{"itemId":29775,"spot":242,"baitId":29716,"biteTime":8,"occurences":1},{"itemId":29769,"spot":242,"baitId":29716,"biteTime":8,"occurences":3},{"itemId":29770,"spot":242,"baitId":29716,"biteTime":8,"occurences":1},{"itemId":29769,"spot":242,"baitId":29716,"biteTime":9,"occurences":2},{"itemId":29762,"spot":242,"baitId":29716,"biteTime":9,"occurences":1},{"itemId":29775,"spot":242,"baitId":29716,"biteTime":10,"occurences":1},{"itemId":29772,"spot":242,"baitId":29716,"biteTime":10,"occurences":1},{"itemId":29767,"spot":242,"baitId":29716,"biteTime":11,"occurences":1},{"itemId":29769,"spot":242,"baitId":29716,"biteTime":11,"occurences":1},{"itemId":29768,"spot":242,"baitId":29716,"biteTime":11,"occurences":1},{"itemId":29769,"spot":242,"baitId":29716,"biteTime":11,"occurences":1},{"itemId":29780,"spot":242,"baitId":29716,"biteTime":12,"occurences":1},{"itemId":29769,"spot":242,"baitId":29716,"biteTime":12,"occurences":1},{"itemId":29768,"spot":242,"baitId":29716,"biteTime":12,"occurences":1},{"itemId":29768,"spot":242,"baitId":29716,"biteTime":12,"occurences":1},{"itemId":29769,"spot":242,"baitId":29716,"biteTime":13,"occurences":1},{"itemId":29768,"spot":242,"baitId":29716,"biteTime":14,"occurences":1},{"itemId":29775,"spot":242,"baitId":29716,"biteTime":15,"occurences":1},{"itemId":29772,"spot":242,"baitId":29716,"biteTime":19,"occurences":1},{"itemId":29775,"spot":242,"baitId":29716,"biteTime":24,"occurences":1},{"itemId":29769,"spot":242,"baitId":29716,"biteTime":33,"occurences":1},{"itemId":29768,"spot":242,"baitId":29716,"biteTime":161,"occurences":1},{"itemId":29775,"spot":242,"baitId":29717,"biteTime":2,"occurences":1},{"itemId":29775,"spot":242,"baitId":29717,"biteTime":3,"occurences":1},{"itemId":29772,"spot":242,"baitId":29717,"biteTime":3,"occurences":1},{"itemId":29775,"spot":242,"baitId":29717,"biteTime":4,"occurences":1},{"itemId":29775,"spot":242,"baitId":29717,"biteTime":4,"occurences":1},{"itemId":29775,"spot":242,"baitId":29717,"biteTime":4,"occurences":1},{"itemId":29775,"spot":242,"baitId":29717,"biteTime":4,"occurences":2},{"itemId":29775,"spot":242,"baitId":29717,"biteTime":4,"occurences":3},{"itemId":29775,"spot":242,"baitId":29717,"biteTime":4,"occurences":2},{"itemId":29775,"spot":242,"baitId":29717,"biteTime":4,"occurences":6},{"itemId":29775,"spot":242,"baitId":29717,"biteTime":4,"occurences":4},{"itemId":29768,"spot":242,"baitId":29717,"biteTime":4,"occurences":1},{"itemId":29775,"spot":242,"baitId":29717,"biteTime":4,"occurences":11},{"itemId":29768,"spot":242,"baitId":29717,"biteTime":5,"occurences":1},{"itemId":29775,"spot":242,"baitId":29717,"biteTime":5,"occurences":17},{"itemId":29768,"spot":242,"baitId":29717,"biteTime":5,"occurences":2},{"itemId":29775,"spot":242,"baitId":29717,"biteTime":5,"occurences":13},{"itemId":29780,"spot":242,"baitId":29717,"biteTime":5,"occurences":1},{"itemId":29768,"spot":242,"baitId":29717,"biteTime":5,"occurences":1},{"itemId":29775,"spot":242,"baitId":29717,"biteTime":5,"occurences":15},{"itemId":29775,"spot":242,"baitId":29717,"biteTime":5,"occurences":14},{"itemId":29768,"spot":242,"baitId":29717,"biteTime":5,"occurences":3},{"itemId":29775,"spot":242,"baitId":29717,"biteTime":5,"occurences":12},{"itemId":29768,"spot":242,"baitId":29717,"biteTime":5,"occurences":4},{"itemId":29775,"spot":242,"baitId":29717,"biteTime":5,"occurences":11},{"itemId":29768,"spot":242,"baitId":29717,"biteTime":5,"occurences":4},{"itemId":29775,"spot":242,"baitId":29717,"biteTime":5,"occurences":7},{"itemId":29780,"spot":242,"baitId":29717,"biteTime":5,"occurences":1},{"itemId":29768,"spot":242,"baitId":29717,"biteTime":5,"occurences":4},{"itemId":29775,"spot":242,"baitId":29717,"biteTime":5,"occurences":4},{"itemId":29780,"spot":242,"baitId":29717,"biteTime":5,"occurences":1},{"itemId":29768,"spot":242,"baitId":29717,"biteTime":5,"occurences":6},{"itemId":29772,"spot":242,"baitId":29717,"biteTime":5,"occurences":1},{"itemId":29775,"spot":242,"baitId":29717,"biteTime":5,"occurences":1},{"itemId":29768,"spot":242,"baitId":29717,"biteTime":5,"occurences":8},{"itemId":29775,"spot":242,"baitId":29717,"biteTime":5,"occurences":2},{"itemId":29768,"spot":242,"baitId":29717,"biteTime":6,"occurences":11},{"itemId":29772,"spot":242,"baitId":29717,"biteTime":6,"occurences":1},{"itemId":29780,"spot":242,"baitId":29717,"biteTime":6,"occurences":1},{"itemId":29768,"spot":242,"baitId":29717,"biteTime":6,"occurences":10},{"itemId":29772,"spot":242,"baitId":29717,"biteTime":6,"occurences":1},{"itemId":29780,"spot":242,"baitId":29717,"biteTime":6,"occurences":2},{"itemId":29768,"spot":242,"baitId":29717,"biteTime":6,"occurences":6},{"itemId":29772,"spot":242,"baitId":29717,"biteTime":6,"occurences":1},{"itemId":29780,"spot":242,"baitId":29717,"biteTime":6,"occurences":4},{"itemId":29768,"spot":242,"baitId":29717,"biteTime":6,"occurences":7},{"itemId":29772,"spot":242,"baitId":29717,"biteTime":6,"occurences":5},{"itemId":29780,"spot":242,"baitId":29717,"biteTime":6,"occurences":3},{"itemId":29768,"spot":242,"baitId":29717,"biteTime":6,"occurences":5},{"itemId":29772,"spot":242,"baitId":29717,"biteTime":6,"occurences":5},{"itemId":29780,"spot":242,"baitId":29717,"biteTime":6,"occurences":6},{"itemId":29768,"spot":242,"baitId":29717,"biteTime":6,"occurences":6},{"itemId":29772,"spot":242,"baitId":29717,"biteTime":6,"occurences":6},{"itemId":29780,"spot":242,"baitId":29717,"biteTime":6,"occurences":2},{"itemId":29767,"spot":242,"baitId":29717,"biteTime":6,"occurences":1},{"itemId":29768,"spot":242,"baitId":29717,"biteTime":6,"occurences":6},{"itemId":29772,"spot":242,"baitId":29717,"biteTime":6,"occurences":8},{"itemId":29780,"spot":242,"baitId":29717,"biteTime":6,"occurences":4},{"itemId":29767,"spot":242,"baitId":29717,"biteTime":6,"occurences":1},{"itemId":29768,"spot":242,"baitId":29717,"biteTime":6,"occurences":4},{"itemId":29772,"spot":242,"baitId":29717,"biteTime":6,"occurences":8},{"itemId":29780,"spot":242,"baitId":29717,"biteTime":6,"occurences":7},{"itemId":29767,"spot":242,"baitId":29717,"biteTime":6,"occurences":1},{"itemId":29768,"spot":242,"baitId":29717,"biteTime":6,"occurences":5},{"itemId":29772,"spot":242,"baitId":29717,"biteTime":6,"occurences":5},{"itemId":29780,"spot":242,"baitId":29717,"biteTime":6,"occurences":3},{"itemId":29767,"spot":242,"baitId":29717,"biteTime":6,"occurences":3},{"itemId":29768,"spot":242,"baitId":29717,"biteTime":6,"occurences":7},{"itemId":29772,"spot":242,"baitId":29717,"biteTime":6,"occurences":4},{"itemId":29780,"spot":242,"baitId":29717,"biteTime":6,"occurences":9},{"itemId":29767,"spot":242,"baitId":29717,"biteTime":7,"occurences":1},{"itemId":29768,"spot":242,"baitId":29717,"biteTime":7,"occurences":3},{"itemId":29772,"spot":242,"baitId":29717,"biteTime":7,"occurences":4},{"itemId":29774,"spot":242,"baitId":29717,"biteTime":7,"occurences":1},{"itemId":29780,"spot":242,"baitId":29717,"biteTime":7,"occurences":5},{"itemId":29767,"spot":242,"baitId":29717,"biteTime":7,"occurences":1},{"itemId":29768,"spot":242,"baitId":29717,"biteTime":7,"occurences":5},{"itemId":29772,"spot":242,"baitId":29717,"biteTime":7,"occurences":9},{"itemId":29774,"spot":242,"baitId":29717,"biteTime":7,"occurences":1},{"itemId":29780,"spot":242,"baitId":29717,"biteTime":7,"occurences":4},{"itemId":29767,"spot":242,"baitId":29717,"biteTime":7,"occurences":2},{"itemId":29768,"spot":242,"baitId":29717,"biteTime":7,"occurences":1},{"itemId":29769,"spot":242,"baitId":29717,"biteTime":7,"occurences":1},{"itemId":29772,"spot":242,"baitId":29717,"biteTime":7,"occurences":4},{"itemId":29780,"spot":242,"baitId":29717,"biteTime":7,"occurences":5},{"itemId":29767,"spot":242,"baitId":29717,"biteTime":7,"occurences":3},{"itemId":29768,"spot":242,"baitId":29717,"biteTime":7,"occurences":1},{"itemId":29769,"spot":242,"baitId":29717,"biteTime":7,"occurences":1},{"itemId":29772,"spot":242,"baitId":29717,"biteTime":7,"occurences":7},{"itemId":29780,"spot":242,"baitId":29717,"biteTime":7,"occurences":9},{"itemId":29767,"spot":242,"baitId":29717,"biteTime":7,"occurences":1},{"itemId":29772,"spot":242,"baitId":29717,"biteTime":7,"occurences":5},{"itemId":29780,"spot":242,"baitId":29717,"biteTime":7,"occurences":8},{"itemId":29767,"spot":242,"baitId":29717,"biteTime":7,"occurences":2},{"itemId":29769,"spot":242,"baitId":29717,"biteTime":7,"occurences":2},{"itemId":29772,"spot":242,"baitId":29717,"biteTime":7,"occurences":7},{"itemId":29774,"spot":242,"baitId":29717,"biteTime":7,"occurences":1},{"itemId":29780,"spot":242,"baitId":29717,"biteTime":7,"occurences":8},{"itemId":29769,"spot":242,"baitId":29717,"biteTime":7,"occurences":1},{"itemId":29772,"spot":242,"baitId":29717,"biteTime":7,"occurences":5},{"itemId":29780,"spot":242,"baitId":29717,"biteTime":7,"occurences":5},{"itemId":29767,"spot":242,"baitId":29717,"biteTime":7,"occurences":1},{"itemId":29769,"spot":242,"baitId":29717,"biteTime":7,"occurences":1},{"itemId":29772,"spot":242,"baitId":29717,"biteTime":7,"occurences":11},{"itemId":29780,"spot":242,"baitId":29717,"biteTime":7,"occurences":7},{"itemId":29772,"spot":242,"baitId":29717,"biteTime":7,"occurences":3},{"itemId":29774,"spot":242,"baitId":29717,"biteTime":7,"occurences":1},{"itemId":29780,"spot":242,"baitId":29717,"biteTime":7,"occurences":6},{"itemId":29769,"spot":242,"baitId":29717,"biteTime":7,"occurences":3},{"itemId":29772,"spot":242,"baitId":29717,"biteTime":7,"occurences":6},{"itemId":29774,"spot":242,"baitId":29717,"biteTime":7,"occurences":1},{"itemId":29780,"spot":242,"baitId":29717,"biteTime":7,"occurences":6},{"itemId":29769,"spot":242,"baitId":29717,"biteTime":8,"occurences":2},{"itemId":29772,"spot":242,"baitId":29717,"biteTime":8,"occurences":5},{"itemId":29774,"spot":242,"baitId":29717,"biteTime":8,"occurences":2},{"itemId":29780,"spot":242,"baitId":29717,"biteTime":8,"occurences":5},{"itemId":29769,"spot":242,"baitId":29717,"biteTime":8,"occurences":4},{"itemId":29772,"spot":242,"baitId":29717,"biteTime":8,"occurences":7},{"itemId":29774,"spot":242,"baitId":29717,"biteTime":8,"occurences":1},{"itemId":29780,"spot":242,"baitId":29717,"biteTime":8,"occurences":4},{"itemId":29769,"spot":242,"baitId":29717,"biteTime":8,"occurences":3},{"itemId":29770,"spot":242,"baitId":29717,"biteTime":8,"occurences":1},{"itemId":29772,"spot":242,"baitId":29717,"biteTime":8,"occurences":7},{"itemId":29780,"spot":242,"baitId":29717,"biteTime":8,"occurences":3},{"itemId":29769,"spot":242,"baitId":29717,"biteTime":8,"occurences":7},{"itemId":29772,"spot":242,"baitId":29717,"biteTime":8,"occurences":6},{"itemId":29780,"spot":242,"baitId":29717,"biteTime":8,"occurences":7},{"itemId":29769,"spot":242,"baitId":29717,"biteTime":8,"occurences":7},{"itemId":29772,"spot":242,"baitId":29717,"biteTime":8,"occurences":7},{"itemId":29774,"spot":242,"baitId":29717,"biteTime":8,"occurences":2},{"itemId":29780,"spot":242,"baitId":29717,"biteTime":8,"occurences":3},{"itemId":29769,"spot":242,"baitId":29717,"biteTime":8,"occurences":5},{"itemId":29770,"spot":242,"baitId":29717,"biteTime":8,"occurences":1},{"itemId":29772,"spot":242,"baitId":29717,"biteTime":8,"occurences":4},{"itemId":29774,"spot":242,"baitId":29717,"biteTime":8,"occurences":3},{"itemId":29780,"spot":242,"baitId":29717,"biteTime":8,"occurences":3},{"itemId":29769,"spot":242,"baitId":29717,"biteTime":8,"occurences":1},{"itemId":29772,"spot":242,"baitId":29717,"biteTime":8,"occurences":1},{"itemId":29780,"spot":242,"baitId":29717,"biteTime":8,"occurences":2},{"itemId":29769,"spot":242,"baitId":29717,"biteTime":8,"occurences":6},{"itemId":29769,"spot":242,"baitId":29717,"biteTime":8,"occurences":6},{"itemId":29770,"spot":242,"baitId":29717,"biteTime":8,"occurences":1},{"itemId":29772,"spot":242,"baitId":29717,"biteTime":8,"occurences":1},{"itemId":29769,"spot":242,"baitId":29717,"biteTime":8,"occurences":3},{"itemId":29770,"spot":242,"baitId":29717,"biteTime":8,"occurences":3},{"itemId":29769,"spot":242,"baitId":29717,"biteTime":9,"occurences":5},{"itemId":29770,"spot":242,"baitId":29717,"biteTime":9,"occurences":1},{"itemId":29769,"spot":242,"baitId":29717,"biteTime":9,"occurences":5},{"itemId":29770,"spot":242,"baitId":29717,"biteTime":9,"occurences":1},{"itemId":29772,"spot":242,"baitId":29717,"biteTime":9,"occurences":1},{"itemId":29769,"spot":242,"baitId":29717,"biteTime":9,"occurences":8},{"itemId":29762,"spot":242,"baitId":29717,"biteTime":9,"occurences":1},{"itemId":29769,"spot":242,"baitId":29717,"biteTime":9,"occurences":4},{"itemId":29770,"spot":242,"baitId":29717,"biteTime":9,"occurences":2},{"itemId":29762,"spot":242,"baitId":29717,"biteTime":9,"occurences":1},{"itemId":29769,"spot":242,"baitId":29717,"biteTime":9,"occurences":3},{"itemId":29772,"spot":242,"baitId":29717,"biteTime":9,"occurences":1},{"itemId":29769,"spot":242,"baitId":29717,"biteTime":9,"occurences":6},{"itemId":29770,"spot":242,"baitId":29717,"biteTime":9,"occurences":1},{"itemId":29762,"spot":242,"baitId":29717,"biteTime":9,"occurences":1},{"itemId":29769,"spot":242,"baitId":29717,"biteTime":9,"occurences":5},{"itemId":29770,"spot":242,"baitId":29717,"biteTime":9,"occurences":1},{"itemId":29762,"spot":242,"baitId":29717,"biteTime":9,"occurences":1},{"itemId":29769,"spot":242,"baitId":29717,"biteTime":9,"occurences":3},{"itemId":29762,"spot":242,"baitId":29717,"biteTime":9,"occurences":1},{"itemId":29769,"spot":242,"baitId":29717,"biteTime":9,"occurences":2},{"itemId":29770,"spot":242,"baitId":29717,"biteTime":9,"occurences":1},{"itemId":29769,"spot":242,"baitId":29717,"biteTime":9,"occurences":4},{"itemId":29770,"spot":242,"baitId":29717,"biteTime":9,"occurences":1},{"itemId":29769,"spot":242,"baitId":29717,"biteTime":10,"occurences":3},{"itemId":29770,"spot":242,"baitId":29717,"biteTime":10,"occurences":1},{"itemId":29769,"spot":242,"baitId":29717,"biteTime":10,"occurences":2},{"itemId":29770,"spot":242,"baitId":29717,"biteTime":10,"occurences":1},{"itemId":29762,"spot":242,"baitId":29717,"biteTime":10,"occurences":1},{"itemId":29769,"spot":242,"baitId":29717,"biteTime":10,"occurences":2},{"itemId":29769,"spot":242,"baitId":29717,"biteTime":10,"occurences":6},{"itemId":29770,"spot":242,"baitId":29717,"biteTime":10,"occurences":1},{"itemId":29769,"spot":242,"baitId":29717,"biteTime":10,"occurences":4},{"itemId":29770,"spot":242,"baitId":29717,"biteTime":10,"occurences":1},{"itemId":29769,"spot":242,"baitId":29717,"biteTime":10,"occurences":3},{"itemId":29770,"spot":242,"baitId":29717,"biteTime":10,"occurences":1},{"itemId":29762,"spot":242,"baitId":29717,"biteTime":10,"occurences":3},{"itemId":29769,"spot":242,"baitId":29717,"biteTime":10,"occurences":4},{"itemId":29770,"spot":242,"baitId":29717,"biteTime":10,"occurences":2},{"itemId":29769,"spot":242,"baitId":29717,"biteTime":10,"occurences":3},{"itemId":29769,"spot":242,"baitId":29717,"biteTime":10,"occurences":3},{"itemId":29762,"spot":242,"baitId":29717,"biteTime":10,"occurences":1},{"itemId":29769,"spot":242,"baitId":29717,"biteTime":10,"occurences":3},{"itemId":29769,"spot":242,"baitId":29717,"biteTime":11,"occurences":3},{"itemId":29762,"spot":242,"baitId":29717,"biteTime":11,"occurences":2},{"itemId":29769,"spot":242,"baitId":29717,"biteTime":11,"occurences":4},{"itemId":29769,"spot":242,"baitId":29717,"biteTime":11,"occurences":5},{"itemId":29762,"spot":242,"baitId":29717,"biteTime":11,"occurences":3},{"itemId":29769,"spot":242,"baitId":29717,"biteTime":11,"occurences":2},{"itemId":29762,"spot":242,"baitId":29717,"biteTime":11,"occurences":1},{"itemId":29769,"spot":242,"baitId":29717,"biteTime":11,"occurences":5},{"itemId":29762,"spot":242,"baitId":29717,"biteTime":11,"occurences":1},{"itemId":29769,"spot":242,"baitId":29717,"biteTime":11,"occurences":1},{"itemId":29762,"spot":242,"baitId":29717,"biteTime":11,"occurences":1},{"itemId":29762,"spot":242,"baitId":29717,"biteTime":11,"occurences":2},{"itemId":29768,"spot":242,"baitId":29717,"biteTime":14,"occurences":1}]}}